basics/decoder_3x8_seq/decoder_3x8_seq.vhd
-------------------------------------------------------
-- Project : 3x8 Priority Decoder
-- Author : Julian Gesche
-- Date : 2020-01-02
-- File : decoder_3x8_seq.vhd
------------------------------------------------------
-- Description : This unit works as 3x8 priority decoder
-------------------------------------------------------
-- /
-------------------------------------------------------

library ieee;
use ieee.std_logic_1164.all;

entity decoder_3x8_seq is
  Port(
    d_in: in std_logic_vector(2 downto 0);
    q_out: out std_logic_vector(7 downto 0)
  );
end;

architecture rtl of decoder_3x8_seq is
begin
  process(d_in)
    begin
      if(d_in="000") then
        q_out <= "00000001";
      elsif (d_in="001") then
        q_out <= "00000010";
      elsif (d_in="010") then
        q_out <= "00000100";
      elsif (d_in="011") then
        q_out <= "00001000";
      elsif (d_in="100") then
        q_out <= "00010000";
      elsif (d_in="101") then
        q_out <= "00100000";
      elsif (d_in="110") then
        q_out <= "01000000";
      elsif (d_in="111") then
        q_out <= "10000000";
      else q_out <= "XXXXXXXX";
      end if;
    end process;
end rtl;

basics/decoder_3x8_seq/tb_decoder_3x8_seq.vhd
-------------------------------------------------------
-- Project : 3x8 Priority Decoder
-- Author : Julian Gesche
-- Date : 2020-01-02
-- File : tb_decoder_3x8_seq.vhd
------------------------------------------------------
-- Description : Testbench for 3x8 priority decoder
-------------------------------------------------------
-- /
-------------------------------------------------------

library ieee;
use ieee.std_logic_1164.all;

entity tb_decoder_3x8_seq is
end;

architecture behavior of tb_decoder_3x8_seq is
  signal d_in: std_logic_vector(2 downto 0);
  signal q_out: std_logic_vector(7 downto 0);
begin
  UUT : entity work.decoder_3x8_seq port map (d_in, q_out);
  process
    begin
       d_in<="000";
       wait for 10 ns;
       d_in<="001";
       wait for 10 ns;
       d_in<="010";
       wait for 10 ns;
       d_in<="011";
       wait for 10 ns;
       d_in<="100";
       wait for 10 ns;
       d_in<="101";
       wait for 10 ns;
       d_in<="110";
       wait for 10 ns;
       d_in<="111";
       wait for 10 ns;
       wait;
    end process;
end behavior;

basics/decoder_3x8_seq/decoder_3x8_seq.vcd
$date
  Sun Apr  5 08:46:22 2020
$end
$version
  GHDL v0
$end
$timescale
  1 fs
$end
$scope module standard $end
$upscope $end
$scope module std_logic_1164 $end
$upscope $end
$scope module tb_decoder_3x8_seq $end
$var reg 3 ! d_in[2:0] $end
$var reg 8 " q_out[7:0] $end
$scope module uut $end
$var reg 3 # d_in[2:0] $end
$var reg 8 $ q_out[7:0] $end
$upscope $end
$upscope $end
$enddefinitions $end
#0
b000 !
b00000001 "
b000 #
b00000001 $
#10000000
b001 !
b00000010 "
b001 #
b00000010 $
#20000000
b010 !
b00000100 "
b010 #
b00000100 $
#30000000
b011 !
b00001000 "
b011 #
b00001000 $
#40000000
b100 !
b00010000 "
b100 #
b00010000 $
#50000000
b101 !
b00100000 "
b101 #
b00100000 $
#60000000
b110 !
b01000000 "
b110 #
b01000000 $
#70000000
b111 !
b10000000 "
b111 #
b10000000 $
